startds/__init__.py
startds/__main__.py
startds/conf/__init__.py
startds/conf/exp_template/.dockerignore-tpl
startds/conf/exp_template/.env-tpl
startds/conf/exp_template/.gitignore-tpl
startds/conf/exp_template/Dockerfile-tpl
startds/conf/exp_template/README.md-tpl
startds/conf/exp_template/requirements.txt-tpl
startds/conf/exp_template/run.py-tpl
startds/conf/exp_template/setup.py-tpl
startds/conf/exp_template/exp_name/__init__.py-tpl
startds/conf/exp_template/exp_name/metadata/data.md-tpl
startds/conf/exp_template/exp_name/metadata/models.md-tpl
startds/conf/exp_template/exp_name/models/.gitkeep-tpl
startds/conf/exp_template/exp_name/notebooks/.gitkeep-tpl
startds/conf/exp_template/exp_name/outputs/figures/.gitkeep-tpl
startds/conf/exp_template/exp_name/src/__init__.py-tpl
startds/conf/exp_template/exp_name/src/_apis/README.md-tpl
startds/conf/exp_template/exp_name/src/_apis/__init__.py-tpl
startds/conf/exp_template/exp_name/src/_apis/cortex/cortex.yaml-tpl
startds/conf/exp_template/exp_name/src/_apis/cortex/main.py-tpl
startds/conf/exp_template/exp_name/src/_apis/cortex/requirements.txt-tpl
startds/conf/exp_template/exp_name/src/_apis/fastapi/Dockerfile-tpl
startds/conf/exp_template/exp_name/src/_apis/fastapi/build.sh-tpl
startds/conf/exp_template/exp_name/src/_apis/fastapi/main.py-tpl
startds/conf/exp_template/exp_name/src/_apis/flask/Dockerfile-tpl
startds/conf/exp_template/exp_name/src/_apis/flask/build.sh-tpl
startds/conf/exp_template/exp_name/src/_apis/flask/main.py-tpl
startds/conf/exp_template/exp_name/src/_apps/README.md-tpl
startds/conf/exp_template/exp_name/src/_apps/__init__.py-tpl
startds/conf/exp_template/exp_name/src/_apps/streamlit/Dockerfile-tpl
startds/conf/exp_template/exp_name/src/_apps/streamlit/build.sh-tpl
startds/conf/exp_template/exp_name/src/_apps/streamlit/main.py-tpl
startds/conf/exp_template/exp_name/src/_orchestrate/__init__.py-tpl
startds/conf/exp_template/exp_name/src/_orchestrate/airflow/dags/dag.py-tpl
startds-0.1.2.dist-info/LICENSE
startds-0.1.2.dist-info/METADATA
startds-0.1.2.dist-info/WHEEL
startds-0.1.2.dist-info/entry_points.txt
startds-0.1.2.dist-info/top_level.txt
startds-0.1.2.dist-info/RECORD
