Metadata-Version: 2.1
Name: startds
Version: 0.1.2
Summary: A data science experiment framework.
Home-page: https://www.dolphyn.io/
Author: Dolphyn
Author-email: support@dolphyn.io
License: MIT
Project-URL: Documentation, https://github.com/dolphynhq/startds
Project-URL: Source, https://github.com/dolphynhq/startds
Platform: UNKNOWN
Classifier: Development Status :: 2 - Pre-Alpha
Classifier: License :: OSI Approved :: MIT License
Classifier: Operating System :: OS Independent
Classifier: Programming Language :: Python
Classifier: Programming Language :: Python :: 3
Classifier: Programming Language :: Python :: 3 :: Only
Classifier: Programming Language :: Python :: 3.6
Classifier: Programming Language :: Python :: 3.7
Classifier: Programming Language :: Python :: 3.8
Classifier: Topic :: Software Development :: Libraries :: Application Frameworks
Classifier: Topic :: Software Development :: Libraries :: Python Modules
Requires-Python: >=3.6
